datasets/__init__.py
datasets/arrow_dataset.py
datasets/arrow_reader.py
datasets/arrow_writer.py
datasets/builder.py
datasets/combine.py
datasets/config.py
datasets/data_files.py
datasets/dataset_dict.py
datasets/distributed.py
datasets/exceptions.py
datasets/fingerprint.py
datasets/hub.py
datasets/info.py
datasets/inspect.py
datasets/iterable_dataset.py
datasets/keyhash.py
datasets/load.py
datasets/naming.py
datasets/search.py
datasets/splits.py
datasets/streaming.py
datasets/table.py
datasets/commands/__init__.py
datasets/commands/convert.py
datasets/commands/convert_to_parquet.py
datasets/commands/datasets_cli.py
datasets/commands/delete_from_hub.py
datasets/commands/env.py
datasets/commands/test.py
datasets/download/__init__.py
datasets/download/download_config.py
datasets/download/download_manager.py
datasets/download/streaming_download_manager.py
datasets/features/__init__.py
datasets/features/audio.py
datasets/features/features.py
datasets/features/image.py
datasets/features/translation.py
datasets/features/video.py
datasets/filesystems/__init__.py
datasets/filesystems/compression.py
datasets/formatting/__init__.py
datasets/formatting/formatting.py
datasets/formatting/jax_formatter.py
datasets/formatting/np_formatter.py
datasets/formatting/polars_formatter.py
datasets/formatting/tf_formatter.py
datasets/formatting/torch_formatter.py
datasets/io/__init__.py
datasets/io/abc.py
datasets/io/csv.py
datasets/io/generator.py
datasets/io/json.py
datasets/io/parquet.py
datasets/io/spark.py
datasets/io/sql.py
datasets/io/text.py
datasets/packaged_modules/__init__.py
datasets/packaged_modules/arrow/__init__.py
datasets/packaged_modules/arrow/arrow.py
datasets/packaged_modules/audiofolder/__init__.py
datasets/packaged_modules/audiofolder/audiofolder.py
datasets/packaged_modules/cache/__init__.py
datasets/packaged_modules/cache/cache.py
datasets/packaged_modules/csv/__init__.py
datasets/packaged_modules/csv/csv.py
datasets_fast-3.1.5.dist-info/AUTHORS
datasets_fast-3.1.5.dist-info/LICENSE
datasets_fast-3.1.5.dist-info/METADATA
datasets_fast-3.1.5.dist-info/WHEEL
datasets_fast-3.1.5.dist-info/entry_points.txt
datasets_fast-3.1.5.dist-info/top_level.txt
datasets_fast-3.1.5.dist-info/RECORD
