Metadata-Version: 2.1
Name: datasets-fast
Version: 3.1.5
Summary: Optimisations for HuggingFace Datasets with array features
Home-page: https://github.com/bioml-tools/fast-datasets
Download-URL: https://github.com/bioml-tools/fast-datasets/tags
Author: HuggingFace Inc., Alex Hawkins-Hooker
License: Apache 2.0
Keywords: datasets machine learning datasets
Classifier: Development Status :: 5 - Production/Stable
Classifier: Intended Audience :: Developers
Classifier: Intended Audience :: Education
Classifier: Intended Audience :: Science/Research
Classifier: License :: OSI Approved :: Apache Software License
Classifier: Operating System :: OS Independent
Classifier: Programming Language :: Python :: 3
Classifier: Programming Language :: Python :: 3.8
Classifier: Programming Language :: Python :: 3.9
Classifier: Programming Language :: Python :: 3.10
Classifier: Programming Language :: Python :: 3.11
Classifier: Topic :: Scientific/Engineering :: Artificial Intelligence
Requires-Python: >=3.8.0
License-File: LICENSE
License-File: AUTHORS
Requires-Dist: filelock
Requires-Dist: numpy >=1.17
Requires-Dist: pyarrow >=15.0.0
Requires-Dist: dill <0.3.9,>=0.3.0
Requires-Dist: pandas
Requires-Dist: requests >=2.32.2
Requires-Dist: tqdm >=4.66.3
Requires-Dist: xxhash
Requires-Dist: multiprocess <0.70.17
Requires-Dist: fsspec[http] <=2024.9.0,>=2023.1.0
Requires-Dist: aiohttp
Requires-Dist: huggingface-hub >=0.23.0
Requires-Dist: packaging
Requires-Dist: pyyaml >=5.1
Provides-Extra: audio
Requires-Dist: soundfile >=0.12.1 ; extra == 'audio'
Requires-Dist: librosa ; extra == 'audio'
Requires-Dist: soxr >=0.4.0 ; (python_version >= "3.9") and extra == 'audio'
Provides-Extra: benchmarks
Requires-Dist: tensorflow ==2.12.0 ; extra == 'benchmarks'
Requires-Dist: torch ==2.0.1 ; extra == 'benchmarks'
Requires-Dist: transformers ==4.30.1 ; extra == 'benchmarks'
Provides-Extra: dev
Requires-Dist: absl-py ; extra == 'dev'
Requires-Dist: decorator ; extra == 'dev'
Requires-Dist: joblib <1.3.0 ; extra == 'dev'
Requires-Dist: joblibspark ; extra == 'dev'
Requires-Dist: pytest ; extra == 'dev'
Requires-Dist: pytest-datadir ; extra == 'dev'
Requires-Dist: pytest-xdist ; extra == 'dev'
Requires-Dist: elasticsearch <8.0.0 ; extra == 'dev'
Requires-Dist: faiss-cpu >=1.8.0.post1 ; extra == 'dev'
Requires-Dist: lz4 ; extra == 'dev'
Requires-Dist: moto[server] ; extra == 'dev'
Requires-Dist: pyspark >=3.4 ; extra == 'dev'
Requires-Dist: py7zr ; extra == 'dev'
Requires-Dist: rarfile >=4.0 ; extra == 'dev'
Requires-Dist: sqlalchemy ; extra == 'dev'
Requires-Dist: s3fs >=2021.11.1 ; extra == 'dev'
Requires-Dist: protobuf <4.0.0 ; extra == 'dev'
Requires-Dist: tiktoken ; extra == 'dev'
Requires-Dist: torch >=2.0.0 ; extra == 'dev'
Requires-Dist: torchdata ; extra == 'dev'
Requires-Dist: soundfile >=0.12.1 ; extra == 'dev'
Requires-Dist: transformers >=4.42.0 ; extra == 'dev'
Requires-Dist: zstandard ; extra == 'dev'
Requires-Dist: polars[timezone] >=0.20.0 ; extra == 'dev'
Requires-Dist: decord ==0.6.0 ; extra == 'dev'
Requires-Dist: Pillow >=9.4.0 ; extra == 'dev'
Requires-Dist: librosa ; extra == 'dev'
Requires-Dist: ruff >=0.3.0 ; extra == 'dev'
Requires-Dist: s3fs ; extra == 'dev'
Requires-Dist: transformers ; extra == 'dev'
Requires-Dist: torch ; extra == 'dev'
Requires-Dist: tensorflow >=2.6.0 ; extra == 'dev'
Requires-Dist: tensorflow >=2.6.0 ; (python_version < "3.10") and extra == 'dev'
Requires-Dist: tensorflow >=2.16.0 ; (python_version >= "3.10") and extra == 'dev'
Requires-Dist: soxr >=0.4.0 ; (python_version >= "3.9") and extra == 'dev'
Requires-Dist: jax >=0.3.14 ; (sys_platform != "win32") and extra == 'dev'
Requires-Dist: jaxlib >=0.3.14 ; (sys_platform != "win32") and extra == 'dev'
Provides-Extra: docs
Requires-Dist: s3fs ; extra == 'docs'
Requires-Dist: transformers ; extra == 'docs'
Requires-Dist: torch ; extra == 'docs'
Requires-Dist: tensorflow >=2.6.0 ; extra == 'docs'
Provides-Extra: jax
Requires-Dist: jax >=0.3.14 ; extra == 'jax'
Requires-Dist: jaxlib >=0.3.14 ; extra == 'jax'
Provides-Extra: quality
Requires-Dist: ruff >=0.3.0 ; extra == 'quality'
Provides-Extra: s3
Requires-Dist: s3fs ; extra == 's3'
Provides-Extra: streaming
Provides-Extra: tensorflow
Requires-Dist: tensorflow >=2.6.0 ; extra == 'tensorflow'
Provides-Extra: tensorflow_gpu
Requires-Dist: tensorflow >=2.6.0 ; extra == 'tensorflow_gpu'
Provides-Extra: tests
Requires-Dist: absl-py ; extra == 'tests'
Requires-Dist: decorator ; extra == 'tests'
Requires-Dist: joblib <1.3.0 ; extra == 'tests'
Requires-Dist: joblibspark ; extra == 'tests'
Requires-Dist: pytest ; extra == 'tests'
Requires-Dist: pytest-datadir ; extra == 'tests'
Requires-Dist: pytest-xdist ; extra == 'tests'
Requires-Dist: elasticsearch <8.0.0 ; extra == 'tests'
Requires-Dist: faiss-cpu >=1.8.0.post1 ; extra == 'tests'
Requires-Dist: lz4 ; extra == 'tests'
Requires-Dist: moto[server] ; extra == 'tests'
Requires-Dist: pyspark >=3.4 ; extra == 'tests'
Requires-Dist: py7zr ; extra == 'tests'
Requires-Dist: rarfile >=4.0 ; extra == 'tests'
Requires-Dist: sqlalchemy ; extra == 'tests'
Requires-Dist: s3fs >=2021.11.1 ; extra == 'tests'
Requires-Dist: protobuf <4.0.0 ; extra == 'tests'
Requires-Dist: tiktoken ; extra == 'tests'
Requires-Dist: torch >=2.0.0 ; extra == 'tests'
Requires-Dist: torchdata ; extra == 'tests'
Requires-Dist: soundfile >=0.12.1 ; extra == 'tests'
Requires-Dist: transformers >=4.42.0 ; extra == 'tests'
Requires-Dist: zstandard ; extra == 'tests'
Requires-Dist: polars[timezone] >=0.20.0 ; extra == 'tests'
Requires-Dist: decord ==0.6.0 ; extra == 'tests'
Requires-Dist: Pillow >=9.4.0 ; extra == 'tests'
Requires-Dist: librosa ; extra == 'tests'
Requires-Dist: tensorflow >=2.6.0 ; (python_version < "3.10") and extra == 'tests'
Requires-Dist: tensorflow >=2.16.0 ; (python_version >= "3.10") and extra == 'tests'
Requires-Dist: soxr >=0.4.0 ; (python_version >= "3.9") and extra == 'tests'
Requires-Dist: jax >=0.3.14 ; (sys_platform != "win32") and extra == 'tests'
Requires-Dist: jaxlib >=0.3.14 ; (sys_platform != "win32") and extra == 'tests'
Provides-Extra: tests_numpy2
Requires-Dist: absl-py ; extra == 'tests_numpy2'
Requires-Dist: decorator ; extra == 'tests_numpy2'
Requires-Dist: joblib <1.3.0 ; extra == 'tests_numpy2'
Requires-Dist: joblibspark ; extra == 'tests_numpy2'
Requires-Dist: pytest ; extra == 'tests_numpy2'
Requires-Dist: pytest-datadir ; extra == 'tests_numpy2'
Requires-Dist: pytest-xdist ; extra == 'tests_numpy2'
Requires-Dist: elasticsearch <8.0.0 ; extra == 'tests_numpy2'
Requires-Dist: lz4 ; extra == 'tests_numpy2'
Requires-Dist: moto[server] ; extra == 'tests_numpy2'
Requires-Dist: pyspark >=3.4 ; extra == 'tests_numpy2'
Requires-Dist: py7zr ; extra == 'tests_numpy2'
Requires-Dist: rarfile >=4.0 ; extra == 'tests_numpy2'
Requires-Dist: sqlalchemy ; extra == 'tests_numpy2'
Requires-Dist: s3fs >=2021.11.1 ; extra == 'tests_numpy2'
Requires-Dist: protobuf <4.0.0 ; extra == 'tests_numpy2'
Requires-Dist: tiktoken ; extra == 'tests_numpy2'
Requires-Dist: torch >=2.0.0 ; extra == 'tests_numpy2'
Requires-Dist: torchdata ; extra == 'tests_numpy2'
Requires-Dist: soundfile >=0.12.1 ; extra == 'tests_numpy2'
Requires-Dist: transformers >=4.42.0 ; extra == 'tests_numpy2'
Requires-Dist: zstandard ; extra == 'tests_numpy2'
Requires-Dist: polars[timezone] >=0.20.0 ; extra == 'tests_numpy2'
Requires-Dist: decord ==0.6.0 ; extra == 'tests_numpy2'
Requires-Dist: Pillow >=9.4.0 ; extra == 'tests_numpy2'
Requires-Dist: soxr >=0.4.0 ; (python_version >= "3.9") and extra == 'tests_numpy2'
Requires-Dist: jax >=0.3.14 ; (sys_platform != "win32") and extra == 'tests_numpy2'
Requires-Dist: jaxlib >=0.3.14 ; (sys_platform != "win32") and extra == 'tests_numpy2'
Provides-Extra: torch
Requires-Dist: torch ; extra == 'torch'
Provides-Extra: vision
Requires-Dist: Pillow >=9.4.0 ; extra == 'vision'
